podping_hivewriter/__init__.py
podping_hivewriter/async_context.py
podping_hivewriter/async_wrapper.py
podping_hivewriter/cli/__init__.py
podping_hivewriter/cli/podping.py
podping_hivewriter/codec/__init__.py
podping_hivewriter/codec/podping_codec.py
podping_hivewriter/constants.py
podping_hivewriter/exceptions.py
podping_hivewriter/hive.py
podping_hivewriter/models/__init__.py
podping_hivewriter/models/hive_operation_id.py
podping_hivewriter/models/internal_podping.py
podping_hivewriter/models/iri_batch.py
podping_hivewriter/models/lighthive_broadcast_response.py
podping_hivewriter/models/medium.py
podping_hivewriter/models/podping_settings.py
podping_hivewriter/models/reason.py
podping_hivewriter/namespace.py
podping_hivewriter/neuron.py
podping_hivewriter/podping_hivewriter.py
podping_hivewriter/podping_settings.py
podping_hivewriter/podping_settings_manager.py
podping_hivewriter-2.1.0.dist-info/LICENSE
podping_hivewriter-2.1.0.dist-info/METADATA
podping_hivewriter-2.1.0.dist-info/WHEEL
podping_hivewriter-2.1.0.dist-info/entry_points.txt
podping_hivewriter-2.1.0.dist-info/RECORD
