Metadata-Version: 2.1
Name: podping-hivewriter
Version: 2.1.0
Summary: This is a tool used to submit RFC 3987-compliant International Resource Identifiers as a Podping notification on the Hive blockchain.
Home-page: http://podping.org/
License: MIT
Keywords: hive,blockchain,podping,podcasting20
Author: Alecks Gates
Author-email: agates@mail.agates.io
Maintainer: Alecks Gates
Maintainer-email: agates@mail.agates.io
Requires-Python: >=3.9,<3.12
Classifier: Development Status :: 5 - Production/Stable
Classifier: Environment :: Console
Classifier: Framework :: AsyncIO
Classifier: Framework :: Pytest
Classifier: License :: OSI Approved :: MIT License
Classifier: Programming Language :: Python :: 3
Classifier: Programming Language :: Python :: 3.9
Classifier: Programming Language :: Python :: 3.10
Classifier: Programming Language :: Python :: 3.11
Classifier: Programming Language :: Python :: Implementation :: CPython
Classifier: Topic :: Software Development :: Libraries :: Python Modules
Requires-Dist: asgiref (>=3.8,<4.0)
Requires-Dist: capnpy (>=0.10.0,<0.11.0)
Requires-Dist: cffi (>=1.14.5,<2.0.0)
Requires-Dist: lighthive (>=0.4.3,<0.5.0)
Requires-Dist: plexo (==1.0.0)
Requires-Dist: podping-schemas (==1.0.1)
Requires-Dist: pydantic (>=1.10.0,<2.0.0)
Requires-Dist: returns (>=0.22.0,<0.23.0)
Requires-Dist: rfc3987 (>=1.3.8,<2.0.0)
Requires-Dist: single-source (>=0.4.0,<0.5.0)
Requires-Dist: typer[all] (>=0.12.0,<0.13.0)
Project-URL: Repository, https://github.com/Podcastindex-org/podping-hivewriter
